examples/atomic_updates.py
examples/batch_operations.py
examples/collection_binding.py
examples/connection_management.py
examples/count_documents.py
examples/create_documents.py
examples/delete_documents.py
examples/document_models.py
examples/index_creation.py
examples/quick_start.py
examples/read_documents.py
examples/update_documents.py
examples/upsert_operations.py
examples/working_with_cursors.py
mongospec/__init__.py
mongospec/_connection.py
mongospec/core.py
mongospec/utils.py
mongospec/document/__init__.py
mongospec/document/document.py
mongospec/document/operations/__init__.py
mongospec/document/operations/base.py
mongospec/document/operations/count.py
mongospec/document/operations/delete.py
mongospec/document/operations/find.py
mongospec/document/operations/insert.py
mongospec/document/operations/update.py
mongospec-0.1.8.dist-info/licenses/LICENSE
tests/conftest.py
tests/test_connection.py
mongospec-0.1.8.dist-info/METADATA
mongospec-0.1.8.dist-info/WHEEL
mongospec-0.1.8.dist-info/top_level.txt
mongospec-0.1.8.dist-info/RECORD
