Metadata-Version: 2.4
Name: mongospec
Version: 0.1.8
Summary: Async MongoDB ODM with msgspec integration and automatic collection binding
Author-email: Diprog <diprog991@gmail.com>
License-Expression: MIT
Project-URL: Repository, https://github.com/diprog/mongospec
Project-URL: Bug Tracker, https://github.com/diprog/mongospec/issues
Project-URL: Documentation, https://github.com/diprog/mongospec#readme
Keywords: mongodb,odm,async,database,asyncio,msgspec,mongojet
Classifier: Operating System :: MacOS
Classifier: Operating System :: Microsoft
Classifier: Operating System :: POSIX :: Linux
Classifier: Development Status :: 4 - Beta
Classifier: Intended Audience :: Developers
Classifier: Programming Language :: Python :: 3.13
Classifier: Topic :: Database
Classifier: Topic :: Database :: Front-Ends
Classifier: Framework :: AsyncIO
Classifier: Typing :: Typed
Requires-Python: >=3.13
License-File: LICENSE
Requires-Dist: mongojet~=0.4.0
Requires-Dist: msgspec~=0.19.0
Dynamic: license-file
